MaterialsTools-0.0.1.dist-info/DESCRIPTION.rst
MaterialsTools-0.0.1.dist-info/METADATA
MaterialsTools-0.0.1.dist-info/RECORD
MaterialsTools-0.0.1.dist-info/WHEEL
MaterialsTools-0.0.1.dist-info/metadata.json
MaterialsTools-0.0.1.dist-info/top_level.txt
ModelingTools/GenerateAbsorbPoint.py
ModelingTools/GenerateSlab.py
ModelingTools/__init__.py
Utils/SurfaceUtils.py
Utils/__init__.py
