Metadata-Version: 2.0
Name: MaterialsTools
Version: 0.0.1
Summary: Some tools for MatCloud platform run python scripts
Home-page: UNKNOWN
Author: xiang2026
Author-email: xiang2026@outlook.com
License: UNKNOWN
Platform: UNKNOWN
